xp_mall/__init__.py
xp_mall/customization_filter.py
xp_mall/emails.py
xp_mall/extensions.py
xp_mall/fakes.py
xp_mall/settings.py
xp_mall/utils.py
xp_mall/admin/__init__.py
xp_mall/admin/admin_module.py
xp_mall/admin/category.py
xp_mall/admin/goods.py
xp_mall/admin/upload.py
xp_mall/mall/__init__.py
xp_mall/mall/buy.py
xp_mall/mall/comment.py
xp_mall/mall/course.py
xp_mall/mall/goods.py
xp_mall/mall/lesson.py
xp_mall/mall/mall.py
xp_mall/member/__init__.py
xp_mall/member/auth.py
xp_mall/member/decorators.py
Flask_MALL-0.1.0.dist-info/METADATA
Flask_MALL-0.1.0.dist-info/WHEEL
Flask_MALL-0.1.0.dist-info/top_level.txt
Flask_MALL-0.1.0.dist-info/RECORD
